PyImbalReg/DataHandler.py
PyImbalReg/GN.py
PyImbalReg/GNHF.py
PyImbalReg/RO.py
PyImbalReg/RU.py
PyImbalReg/WERCS.py
PyImbalReg/__init__.py
PyImbalReg/train_test_split.py
PyImbalReg-0.0.3.dist-info/LICENSE
PyImbalReg-0.0.3.dist-info/METADATA
PyImbalReg-0.0.3.dist-info/WHEEL
PyImbalReg-0.0.3.dist-info/top_level.txt
PyImbalReg-0.0.3.dist-info/RECORD
