Metadata-Version: 2.1
Name: PyImbalReg
Version: 0.0.3
Summary: Pre-processing technics for imbalanced datasets in regression modelling
Home-page: https://github.com/vd1371/PyImbalReg
Author: Vahid Asghari
Author-email: vd1371@gmail.com
License: UNKNOWN
Keywords: PyImbalReg,imblanaced regression,imbalanced data,pre-processing,data augmentation,undersampling,over-sampling,synthetic data,regression
Platform: UNKNOWN
Classifier: Programming Language :: Python :: 3
Classifier: License :: OSI Approved :: GNU General Public License v3 (GPLv3)
Classifier: Operating System :: OS Independent
Requires-Python: >=3.6
